lib8relind/__init__.py
lib8relind-0.1.dist-info/LICENSE
lib8relind-0.1.dist-info/METADATA
lib8relind-0.1.dist-info/WHEEL
lib8relind-0.1.dist-info/top_level.txt
lib8relind-0.1.dist-info/RECORD
