Metadata-Version: 2.1
Name: lib8relind
Version: 0.1
Summary: A set of functions to control 8-Relay board
Home-page: https://github.com/zhangevanone/relind8-pylib
Author: Stcoe
Author-email: evanone@163.com
License: MIT
Classifier: Programming Language :: Python :: 3
Classifier: License :: OSI Approved :: MIT License
Classifier: Operating System :: OS Independent
License-File: LICENSE
